{ "author": { "name": "Jack Bates" },
  "bugs": "https://github.com/jablko/cellect/issues",
  "demo": "http://nottheoilrig.com/cellect",
  "dependencies": { "jquery": ">=1.7" },
  "description": "Select data in tables the same way you select cells in a spreadsheet.",
  "docs": "http://nottheoilrig.com/cellect",
  "homepage": "http://nottheoilrig.com/cellect",
  "keywords": ["selection", "spreadsheet", "table"],
  "licenses": [{ "type": "MIT",
    "url": "http://opensource.org/licenses/MIT" }],
  "name": "cellect",
  "title": "Cellect",
  "version": "1.0.5" }
